{"contents":"{\"id\":1060205,\"slow_mode\":{\"enabled\":true,\"message_interval\":1},\"subscribers_mode\":{\"enabled\":false},\"followers_mode\":{\"enabled\":true,\"min_duration\":1},\"emotes_mode\":{\"enabled\":false},\"advanced_bot_protection\":{\"enabled\":false,\"remaining_time\":0},\"account_age\":{\"enabled\":false,\"min_duration\":0},\"pinned_message\":null,\"show_quick_emotes\":{\"enabled\":false},\"show_banners\":{\"enabled\":false},\"gifts_enabled\":{\"enabled\":false},\"gifts_week_enabled\":{\"enabled\":false},\"gifts_month_enabled\":{\"enabled\":false}}","status":{"url":"https://kick.com/api/v2/channels/iabs/chatroom","content_type":"application/json","http_code":200,"response_time":184,"content_length":502}}